tpsms/__init__.py
tpsms/act.py
tpsms/authenticate.py
tpsms/client.py
tpsms/execute.py
tpsms/client/__init__.py
tpsms/client/encryption.py
tpsms/client/fetch_busy.py
tpsms/client/fetch_cgi_gdpr.py
tpsms/client/fetch_info.py
tpsms/client/fetch_public_key.py
tpsms/client/fetch_session_id.py
tpsms/client/fetch_token_id.py
tpsms-0.1.2.dist-info/METADATA
tpsms-0.1.2.dist-info/WHEEL
tpsms-0.1.2.dist-info/top_level.txt
tpsms-0.1.2.dist-info/RECORD
