Metadata-Version: 2.4
Name: tpsms
Version: 0.1.2
Summary: A Python client for TP-Link router SMS functionality
Home-page: https://github.com/mosiiisom/tpsms
Author: Mostafa
Author-email: himosiiisom@gmail.com
Classifier: Programming Language :: Python :: 3
Classifier: License :: OSI Approved :: MIT License
Classifier: Operating System :: OS Independent
Requires-Python: >=3.7
Requires-Dist: requests>=2.28.0
Dynamic: author
Dynamic: author-email
Dynamic: classifier
Dynamic: description
Dynamic: description-content-type
Dynamic: home-page
Dynamic: requires-dist
Dynamic: requires-python
Dynamic: summary
